facrud_router/__init__.py
facrud_router/generics.py
facrud_router/logger.py
facrud_router/mixins.py
facrud_router/routers.py
facrud_router/utils.py
facrud_router-0.1.2.dist-info/LICENSE
facrud_router-0.1.2.dist-info/WHEEL
facrud_router-0.1.2.dist-info/METADATA
facrud_router-0.1.2.dist-info/RECORD
